FindOrg/__init__.py
FindOrg/main.py
FindOrg-0.6.dist-info/METADATA
FindOrg-0.6.dist-info/WHEEL
FindOrg-0.6.dist-info/top_level.txt
FindOrg-0.6.dist-info/RECORD
