Metadata-Version: 2.1
Name: FindOrg
Version: 0.6
